BoneMet/__init__.py
tests/__init__.py
BoneMet-0.0.9.dist-info/LICENSE
BoneMet-0.0.9.dist-info/METADATA
BoneMet-0.0.9.dist-info/WHEEL
BoneMet-0.0.9.dist-info/top_level.txt
BoneMet-0.0.9.dist-info/RECORD
