Metadata-Version: 2.1
Name: BoneMet
Version: 0.0.9
Summary: Coming Soon!
Home-page: https://github.com/BoneMet/BoneMet
Author: Anonymous
Author-email: oakmates@gmail.com
Classifier: Programming Language :: Python :: 3
Classifier: License :: OSI Approved :: MIT License
Classifier: Operating System :: OS Independent
Requires-Python: >=3.6
License-File: LICENSE
Requires-Dist: requests
Requires-Dist: numpy
